xorgate.v
// Code your design here
module xorgate (a,b,c);
  input a,b;
  output c;
  
  // estrutural:
  wire      abar, bbar, t1, t2;
  not invA (abar, a);
  not invB (bbar, b);
  and and1 (t1, a, bbar);
  and and2 (t2, b, abar);
  or  or1 (c, t1, t2);

 

  // comportamental
  //assign c=a^b;
endmodule

xorgate_tb.v
module xorgate_tb;
  reg t_a,t_b;
  wire t_c;
  // instantiate the module, map connecetions
  xorgate xorg( .a(t_a), .b(t_b), .c(t_c) );
  initial
    begin
       $dumpfile("dump.vcd");
  		$dumpvars(1);
    end
  
  // mensagem: galo: 01100111 01100001 01101100 01101111 (a)
  // OTP: 00110100 11100000 11111100 10010100            (b)
  // MENSAGEM CIFRADA COM O OTP ACIMA: 
  
  initial
    begin
      $monitor($time,"  ",t_a,t_b," output= ", t_c);
      
      //bit #1
      t_a = 1'b0;
      t_b = 1'b0;
      
      #1
      //bit #2
      t_a = 1'b1;
      t_b = 1'b0;
      
      #1
      //bit #3
      t_a = 1'b1;
      t_b = 1'b1;
      
      #1
      //bit #4
      t_a = 1'b0;
      t_b = 1'b0;
      
      #1
      //bit #5
      t_a = 1'b0;
      t_b = 1'b0;
      
      #3
      t_a = 1'b1;
      t_b = 1'b0;
      
      #2
      t_a = 1'b1;
      t_b = 1'b1;
      
      #2
      t_a = 1'b0;
      t_b = 1'b0;
      
      #2
      t_a = 1'b1;
      t_b = 1'b1;
      
            
      #1
      t_a = 1'b1;
      t_b = 1'b0;
      
      #1
      t_a = 1'b0;
      t_b = 1'b1;
      
      #1
      t_a = 1'b1;
      t_b = 1'b0;
      
      #1
      t_a = 1'b0;
      t_b = 1'b1;
      
      #1
      t_a = 1'b1;
      t_b = 1'b0;
      
      #1
      t_a = 1'b0;
      t_b = 1'b1;
      
      #1
      t_a = 1'b1;
      t_b = 1'b0;
      
      #1
      t_a = 1'b0;
      t_b = 1'b1;
      
      #5
      $display("Aeee Garoto! Turma ISL rocks.");
    end
endmodule

dump.vcd
$date
	Mon Sep 23 17:47:02 2024
$end
$version
	Icarus Verilog
$end
$timescale
	1s
$end
$scope module xorgate_tb $end
$var wire 1 ! t_c $end
$var reg 1 " t_a $end
$var reg 1 # t_b $end
$upscope $end
$enddefinitions $end
$comment Show the parameter values. $end
$dumpall
$end
#0
$dumpvars
0#
0"
0!
$end
#1
1!
1"
#2
0!
1#
#3
0#
0"
#7
1!
1"
#9
0!
1#
#11
0#
0"
#13
0!
1#
1"
#14
1!
0#
#15
1#
0"
#16
1!
0#
1"
#17
1#
0"
#18
1!
0#
1"
#19
1#
0"
#20
1!
0#
1"
#21
1#
0"
